pysqler/__init__.py
pysqler/__version__.py
pysqler/writer.py
pysqler/helper/__init__.py
pysqler/helper/common.py
pysqler/helper/expression.py
pysqler/helper/filter.py
pysqler/helper/into.py
pysqler/helper/strings.py
pysqler/helper/where.py
pysqler-1.0.1.dist-info/LICENSE
pysqler-1.0.1.dist-info/METADATA
pysqler-1.0.1.dist-info/WHEEL
pysqler-1.0.1.dist-info/top_level.txt
pysqler-1.0.1.dist-info/RECORD
