Metadata-Version: 2.1
Name: pysqler
Version: 1.0.1
Summary: Easy to write sql
Home-page: https://github.com/tingxin/pysqler
Author: barry.xu
Author-email: friendship-119@163.com
License: MIT
Platform: UNKNOWN
Classifier: License :: OSI Approved :: MIT License
Classifier: Programming Language :: Python
Classifier: Programming Language :: Python :: 3
Classifier: Programming Language :: Python :: 3.6
Classifier: Programming Language :: Python :: Implementation :: CPython
Classifier: Programming Language :: Python :: Implementation :: PyPy
Requires-Python: >=3.6.0
